README.md
setup.py
DiscPy/__init__.py
DiscPy/disc_api.py
DiscPy/exceptions.py
DiscPy/models.py
DiscPy/rest_adapter.py
DiscPy.egg-info/PKG-INFO
DiscPy.egg-info/SOURCES.txt
DiscPy.egg-info/dependency_links.txt
DiscPy.egg-info/requires.txt
DiscPy.egg-info/top_level.txt