Metadata-Version: 1.1
Name: DiscPy
Version: 0.1.0
Summary: A example Python package
Home-page: https://github.com/Chaaronn/DiscPy
Author: Matt Voce
Author-email: mattvoce117@gmail.com
License: MIT License
Platform: UNKNOWN
Classifier: Development Status :: 1 - Planning
Classifier: Intended Audience :: Developers
Classifier: License :: OSI Approved :: MIT License
Classifier: Operating System :: OS Independent
Classifier: Programming Language :: Python :: 3.7
